django_google_optimize/__init__.py
django_google_optimize/admin.py
django_google_optimize/apps.py
django_google_optimize/middleware.py
django_google_optimize/migrations/0001_initial.py
django_google_optimize/migrations/__init__.py
django_google_optimize/models.py
django_google_optimize/utils.py
django_google_optimize-0.3.0.dist-info/LICENSE
django_google_optimize-0.3.0.dist-info/WHEEL
django_google_optimize-0.3.0.dist-info/METADATA
django_google_optimize-0.3.0.dist-info/RECORD
