Metadata-Version: 2.1
Name: django-google-optimize
Version: 0.3.0
Summary: Django-google-optimize is a reusable Django application designed to make running server side Google Optimize A/B test easy.
Home-page: https://github.com/adinhodovic/django-google-optimize
License: MIT
Keywords: A/B Testing,Google Optimize,Django,Server Side,KPI
Author: Adin Hodovic
Author-email: hodovicadin@gmail.com
Requires-Python: >=3.7,<4.0
Classifier: Development Status :: 5 - Production/Stable
Classifier: Environment :: Web Environment
Classifier: Framework :: Django
Classifier: Framework :: Django :: 2.2
Classifier: Framework :: Django :: 3.0
Classifier: Framework :: Django :: 3.1
Classifier: Intended Audience :: Developers
Classifier: License :: OSI Approved :: MIT License
Classifier: Operating System :: OS Independent
Classifier: Programming Language :: Python
Classifier: Programming Language :: Python :: 3
Classifier: Programming Language :: Python :: 3.7
Classifier: Programming Language :: Python :: 3.8
Classifier: Programming Language :: Python :: 3.9
Requires-Dist: django (>=2.2)
Project-URL: Documentation, https://github.com/adinhodovic/django-google-optimize
Project-URL: Repository, https://github.com/adinhodovic/django-google-optimize
